{
	"archive" : {},
	"artifacts" : 
	[
		{
			"path" : "libjpge.a"
		}
	],
	"backtrace" : 1,
	"backtraceGraph" : 
	{
		"commands" : 
		[
			"add_library"
		],
		"files" : 
		[
			"CMakeLists.txt"
		],
		"nodes" : 
		[
			{
				"file" : 0
			},
			{
				"command" : 0,
				"file" : 0,
				"line" : 13,
				"parent" : 0
			}
		]
	},
	"compileGroups" : 
	[
		{
			"compileCommandFragments" : 
			[
				{
					"fragment" : "-Wall -Wextra -O3 -fno-limit-debug-info  -fPIC"
				}
			],
			"language" : "CXX",
			"sourceIndexes" : 
			[
				0
			],
			"sysroot" : 
			{
				"path" : "C:/Users/lukad/AppData/Local/Android/Sdk/ndk/23.1.7779620/toolchains/llvm/prebuilt/windows-x86_64/sysroot"
			}
		}
	],
	"id" : "jpge::@6890427a1f51a3e7e1df",
	"name" : "jpge",
	"nameOnDisk" : "libjpge.a",
	"paths" : 
	{
		"build" : ".",
		"source" : "."
	},
	"sourceGroups" : 
	[
		{
			"name" : "Source Files",
			"sourceIndexes" : 
			[
				0
			]
		}
	],
	"sources" : 
	[
		{
			"backtrace" : 1,
			"compileGroupIndex" : 0,
			"path" : "C:/Users/lukad/Desktop/flutterapps/straighten/native/jpge/jpge.cpp",
			"sourceGroupIndex" : 0
		}
	],
	"type" : "STATIC_LIBRARY"
}
